{
  "layout": [
    {
      "type": "loading_dock",
      "x": 2.0,
      "y": 246,
      "width": 20,
      "height": 8
    },
    {
      "type": "loading_dock",
      "x": 52.8,
      "y": 246,
      "width": 20,
      "height": 8
    },
    {
      "type": "loading_dock",
      "x": 103.6,
      "y": 246,
      "width": 20,
      "height": 8
    },
    {
      "type": "loading_dock",
      "x": 154.4,
      "y": 246,
      "width": 20,
      "height": 8
    },
    {
      "type": "loading_dock",
      "x": 205.2,
      "y": 246,
      "width": 20,
      "height": 8
    },
    {
      "type": "loading_dock",
      "x": 256.0,
      "y": 246,
      "width": 20,
      "height": 8
    },
    {
      "type": "loading_dock",
      "x": 306.8,
      "y": 246,
      "width": 20,
      "height": 8
    },
    {
      "type": "loading_dock",
      "x": 357.6,
      "y": 246,
      "width": 20,
      "height": 8
    },
    {
      "type": "loading_dock",
      "x": 408.4,
      "y": 246,
      "width": 20,
      "height": 8
    },
    {
      "type": "loading_dock",
      "x": 459.2,
      "y": 246,
      "width": 20,
      "height": 8
    },
    {
      "type": "loading_dock",
      "x": 510.0,
      "y": 246,
      "width": 20,
      "height": 8
    },
    {
      "type": "storage_aisle",
      "x": 10.0,
      "y": 5,
      "width": 10,
      "height": 80
    },
    {
      "type": "storage_aisle",
      "x": 54.72727272727273,
      "y": 5,
      "width": 10,
      "height": 80
    },
    {
      "type": "storage_aisle",
      "x": 99.45454545454545,
      "y": 5,
      "width": 10,
      "height": 80
    },
    {
      "type": "storage_aisle",
      "x": 144.1818181818182,
      "y": 5,
      "width": 10,
      "height": 80
    },
    {
      "type": "storage_aisle",
      "x": 188.9090909090909,
      "y": 5,
      "width": 10,
      "height": 80
    },
    {
      "type": "storage_aisle",
      "x": 233.63636363636363,
      "y": 5,
      "width": 10,
      "height": 80
    },
    {
      "type": "storage_aisle",
      "x": 278.3636363636364,
      "y": 5,
      "width": 10,
      "height": 80
    },
    {
      "type": "storage_aisle",
      "x": 323.09090909090907,
      "y": 5,
      "width": 10,
      "height": 80
    },
    {
      "type": "storage_aisle",
      "x": 367.8181818181818,
      "y": 5,
      "width": 10,
      "height": 80
    },
    {
      "type": "storage_aisle",
      "x": 412.54545454545456,
      "y": 5,
      "width": 10,
      "height": 80
    },
    {
      "type": "storage_aisle",
      "x": 457.27272727272725,
      "y": 5,
      "width": 10,
      "height": 80
    },
    {
      "type": "storage_aisle",
      "x": 502.0,
      "y": 5,
      "width": 10,
      "height": 80
    },
    {
      "type": "packing_station",
      "x": 467,
      "y": 5.0,
      "width": 40,
      "height": 10
    },
    {
      "type": "packing_station",
      "x": 467,
      "y": 40.142857142857146,
      "width": 40,
      "height": 10
    },
    {
      "type": "packing_station",
      "x": 467,
      "y": 75.28571428571429,
      "width": 40,
      "height": 10
    },
    {
      "type": "packing_station",
      "x": 467,
      "y": 110.42857142857143,
      "width": 40,
      "height": 10
    },
    {
      "type": "packing_station",
      "x": 467,
      "y": 145.57142857142858,
      "width": 40,
      "height": 10
    },
    {
      "type": "packing_station",
      "x": 467,
      "y": 180.71428571428572,
      "width": 40,
      "height": 10
    },
    {
      "type": "packing_station",
      "x": 467,
      "y": 215.85714285714286,
      "width": 40,
      "height": 10
    },
    {
      "type": "packing_station",
      "x": 467,
      "y": 251.0,
      "width": 40,
      "height": 10
    }
  ],
  "obstacles": [
    {
      "type": "rectangle",
      "x": 419.8299059171958,
      "y": 91.02844064662843,
      "width": 25.41830031318071,
      "height": 33.194951562378904
    },
    {
      "type": "rectangle",
      "x": 252.685502042806,
      "y": 128.9172374925036,
      "width": 19.292077765156122,
      "height": 38.72811218097673
    },
    {
      "type": "rectangle",
      "x": 388.7431871669093,
      "y": 139.408682643237,
      "width": 26.175998122769442,
      "height": 16.6376482728328
    },
    {
      "type": "rectangle",
      "x": 325.3083883384165,
      "y": 121.67665446469275,
      "width": 26.166665472014337,
      "height": 10.17621356653175
    },
    {
      "type": "rectangle",
      "x": 354.13989030177964,
      "y": 196.66596634171682,
      "width": 37.97672778636135,
      "height": 21.227342484444762
    },
    {
      "type": "rectangle",
      "x": 144.80835718981535,
      "y": 160.14199765503093,
      "width": 36.114983658152504,
      "height": 13.303335347698049
    },
    {
      "type": "rectangle",
      "x": 335.8115352424063,
      "y": 184.12986165381744,
      "width": 30.188101574997575,
      "height": 17.727772987618533
    },
    {
      "type": "rectangle",
      "x": 436.8222677324632,
      "y": 101.78041291078888,
      "width": 15.460232731356829,
      "height": 19.661889784873026
    },
    {
      "type": "rectangle",
      "x": 348.5057873640099,
      "y": 200.73034602338606,
      "width": 32.39692360421225,
      "height": 11.870501469504292
    },
    {
      "type": "rectangle",
      "x": 221.91853236868278,
      "y": 113.02438922693715,
      "width": 22.23747440354984,
      "height": 39.74148996695443
    },
    {
      "type": "rectangle",
      "x": 177.08768664635528,
      "y": 96.687475315266,
      "width": 20.54879416298148,
      "height": 31.444349992757797
    },
    {
      "type": "rectangle",
      "x": 143.92055098619943,
      "y": 145.89386120463342,
      "width": 19.477570130558973,
      "height": 39.964138346949426
    },
    {
      "type": "rectangle",
      "x": 87.42906109941877,
      "y": 116.06190032752033,
      "width": 32.058043329519194,
      "height": 38.31036852236079
    },
    {
      "type": "rectangle",
      "x": 490.92127785131316,
      "y": 125.69941023149293,
      "width": 13.974328388516852,
      "height": 16.26043576742439
    },
    {
      "type": "rectangle",
      "x": 227.90600369559465,
      "y": 189.83954536660573,
      "width": 13.301594758326484,
      "height": 25.069607147950165
    }
  ],
  "pillars": [
    {
      "type": "pillar",
      "x": 76.45072240961413,
      "y": 123.30698444965583,
      "width": 26.209435413222995,
      "height": 26.210702266888138
    },
    {
      "type": "pillar",
      "x": 221.4442869003538,
      "y": 101.31376026955367,
      "width": 21.203472435117007,
      "height": 21.530255220213963
    },
    {
      "type": "pillar",
      "x": 137.32942402601694,
      "y": 42.234783863193115,
      "width": 27.336620808382346,
      "height": 20.735715500615072
    },
    {
      "type": "pillar",
      "x": 309.5643302710602,
      "y": 52.130062821524554,
      "width": 25.080881384605885,
      "height": 25.792511525815144
    },
    {
      "type": "pillar",
      "x": 44.69248345036213,
      "y": 131.2195624166819,
      "width": 24.175776484229303,
      "height": 24.66814180599299
    },
    {
      "type": "pillar",
      "x": 467.698993304267,
      "y": 21.84647213236451,
      "width": 22.28517562664769,
      "height": 20.357297197814656
    },
    {
      "type": "pillar",
      "x": 48.9619185178632,
      "y": 120.77902784563585,
      "width": 27.304802408534588,
      "height": 25.026299236106215
    },
    {
      "type": "pillar",
      "x": 451.6133905235578,
      "y": 224.42832955310075,
      "width": 24.342179614794833,
      "height": 25.480164067044672
    },
    {
      "type": "pillar",
      "x": 213.76506448737484,
      "y": 177.52025161281654,
      "width": 26.623180737805964,
      "height": 23.54130272076084
    },
    {
      "type": "pillar",
      "x": 314.9680205219812,
      "y": 222.95806213845808,
      "width": 26.286906188021035,
      "height": 20.979909211456427
    },
    {
      "type": "pillar",
      "x": 44.6487566195191,
      "y": 187.88820134188674,
      "width": 22.36951967063015,
      "height": 23.927237470201163
    },
    {
      "type": "pillar",
      "x": 83.15882430433987,
      "y": 67.36393944033813,
      "width": 22.89496303791875,
      "height": 21.6399808241071
    },
    {
      "type": "pillar",
      "x": 416.47847803860066,
      "y": 207.27750095235567,
      "width": 20.070625228686634,
      "height": 27.487555976570334
    },
    {
      "type": "pillar",
      "x": 359.5952299956793,
      "y": 148.9591437328905,
      "width": 23.02144911808179,
      "height": 24.741303614194493
    },
    {
      "type": "pillar",
      "x": 438.9035186526263,
      "y": 167.32537099857916,
      "width": 22.676177223684753,
      "height": 23.89271280785603
    },
    {
      "type": "pillar",
      "x": 432.4921534112722,
      "y": 97.42003052683003,
      "width": 20.76246135401603,
      "height": 22.06278270177169
    },
    {
      "type": "pillar",
      "x": 202.83688815825198,
      "y": 173.07397998763847,
      "width": 22.045109984787782,
      "height": 23.469313673719093
    },
    {
      "type": "pillar",
      "x": 187.562076799399,
      "y": 108.69797501663757,
      "width": 21.33084051381747,
      "height": 28.548211188166558
    },
    {
      "type": "pillar",
      "x": 459.6628592895537,
      "y": 110.91316573138747,
      "width": 21.301536970709083,
      "height": 22.72197376460728
    },
    {
      "type": "pillar",
      "x": 303.21649183184445,
      "y": 192.1921342148964,
      "width": 21.524266173093686,
      "height": 25.521470351732273
    },
    {
      "type": "pillar",
      "x": 98.48410476513509,
      "y": 116.79980582259279,
      "width": 24.285688244951665,
      "height": 29.580869515395115
    },
    {
      "type": "pillar",
      "x": 293.7451484034678,
      "y": 22.783826483833337,
      "width": 24.01594208770407,
      "height": 22.788163745855844
    },
    {
      "type": "pillar",
      "x": 356.01489546733364,
      "y": 69.92993036094984,
      "width": 24.951479078272804,
      "height": 24.740719855085935
    },
    {
      "type": "pillar",
      "x": 476.2163502846605,
      "y": 106.4296329884472,
      "width": 22.170888734920588,
      "height": 22.055806154418086
    },
    {
      "type": "pillar",
      "x": 213.2902822328019,
      "y": 93.9777133265746,
      "width": 29.58684969243783,
      "height": 28.961065597258337
    },
    {
      "type": "pillar",
      "x": 387.4691208461037,
      "y": 107.79990758534281,
      "width": 26.609641720351465,
      "height": 29.33981338353756
    },
    {
      "type": "pillar",
      "x": 294.81150565764636,
      "y": 19.13722444365048,
      "width": 24.939436141326404,
      "height": 22.553950124150788
    },
    {
      "type": "pillar",
      "x": 252.92274551053686,
      "y": 139.52271595376885,
      "width": 25.71473453511247,
      "height": 20.91479245484502
    },
    {
      "type": "pillar",
      "x": 308.1913121242867,
      "y": 124.2853860658832,
      "width": 27.72641369132929,
      "height": 25.25112028155413
    },
    {
      "type": "pillar",
      "x": 217.38356458452725,
      "y": 88.99547448724779,
      "width": 22.65582435237804,
      "height": 23.10978491736091
    },
    {
      "type": "pillar",
      "x": 459.13090366302407,
      "y": 137.38591802254922,
      "width": 25.673183798344112,
      "height": 24.12875170299725
    },
    {
      "type": "pillar",
      "x": 112.57124000424866,
      "y": 103.15396565703641,
      "width": 24.74086027042263,
      "height": 29.954995385290914
    }
  ]
}